{
  "tag": "Decrypt",
  "value": [
    {
      "tag": "UniqueIdentifier",
      "type": "TextString",
      "value": "{{key_id}}"
    },
    {
      "tag": "CryptographicParameters",
      "value": [
        {
          "tag": "BlockCipherMode",
          "type": "Enumeration",
          "value": "ECB"
        },
        {
          "tag": "PaddingMethod",
          "type": "Enumeration",
          "value": "None"
        },
        {
          "tag": "CryptographicAlgorithm",
          "type": "Enumeration",
          "value": "AES"
        }
      ]
    },
    {
      "tag": "Data",
      "type": "ByteString",
      "value": "BD334F1D6E45F25FF712A214571FA5CC"
    }
  ]
}
